ckanext/__init__.py
ckanext/nhm/__init__.py
ckanext/nhm/cli.py
ckanext/nhm/plugin.py
ckanext/nhm/settings.py
ckanext/nhm/dcat/__init__.py
ckanext/nhm/dcat/profiles.py
ckanext/nhm/dcat/specimen_records.py
ckanext/nhm/dcat/utils.py
ckanext/nhm/lib/__init__.py
ckanext/nhm/lib/dwc.py
ckanext/nhm/lib/eml.py
ckanext/nhm/lib/external_links.py
ckanext/nhm/lib/filter_options.py
ckanext/nhm/lib/form.py
ckanext/nhm/lib/helpers.py
ckanext/nhm/lib/jinja_extensions.py
ckanext/nhm/lib/record.py
ckanext/nhm/lib/resource_view.py
ckanext/nhm/lib/taxonomy.py
ckanext/nhm/logic/__init__.py
ckanext/nhm/logic/action.py
ckanext/nhm/logic/schema.py
ckanext/nhm/logic/validators.py
ckanext/nhm/routes/__init__.py
ckanext/nhm/routes/about.py
ckanext/nhm/routes/bbcm.py
ckanext/nhm/routes/beetle_iiif.py
ckanext/nhm/routes/help.py
ckanext/nhm/routes/legal.py
ckanext/nhm/routes/misc.py
ckanext/nhm/routes/object.py
ckanext/nhm/routes/record.py
ckanext/nhm/routes/statistics.py
ckanext/nhm/src/tdwg_dwcterms.xsd
ckanext/nhm/views/__init__.py
ckanext/nhm/views/default.py
ckanext/nhm/views/dwc.py
ckanext/nhm/views/indexlot.py
ckanext/nhm/views/specimen.py
docs/_scripts/gen_api_pages.py
ckanext_nhm-4.0.4.dist-info/LICENSE
ckanext_nhm-4.0.4.dist-info/METADATA
ckanext_nhm-4.0.4.dist-info/WHEEL
ckanext_nhm-4.0.4.dist-info/entry_points.txt
ckanext_nhm-4.0.4.dist-info/top_level.txt
ckanext_nhm-4.0.4.dist-info/RECORD
