Metadata-Version: 2.1
Name: ckanext-nhm
Version: 4.0.4
Summary: A CKAN extension for the Natural History Museum's Data Portal.
Author-email: Natural History Museum <data@nhm.ac.uk>
License: GPL-3.0-or-later
Project-URL: repository, https://github.com/NaturalHistoryMuseum/ckanext-nhm
Project-URL: changelog, https://github.com/NaturalHistoryMuseum/ckanext-nhm/blob/main/CHANGELOG.md
Keywords: CKAN,data,nhm
Classifier: Development Status :: 5 - Production/Stable
Classifier: License :: OSI Approved :: GNU General Public License v3 (GPLv3)
Classifier: Programming Language :: Python
Classifier: Programming Language :: Python :: 3 :: Only
Classifier: Programming Language :: Python :: 3.6
Classifier: Programming Language :: Python :: 3.7
Classifier: Programming Language :: Python :: 3.8
Requires-Python: >=3.6
License-File: LICENSE
Requires-Dist: importlib-resources
Requires-Dist: ckantools (>=0.3.0)
Requires-Dist: cachetools (>=4.2.4)
Requires-Dist: lxml (>=4.4.2)
Requires-Dist: elasticsearch-dsl (<7.0.0,>=6.0.0)
Requires-Dist: ckanext-ckanpackager (>=2.2.0)
Requires-Dist: ckanext-contact (>=2.1.0)
Requires-Dist: ckanext-doi (>=3.1.0)
Requires-Dist: ckanext-gallery (>=2.2.0)
Requires-Dist: ckanext-gbif (>=2.1.0)
Requires-Dist: ckanext-graph (>=2.1.0)
Requires-Dist: ckanext-iiif (>=3.0.1)
Requires-Dist: ckanext-ldap (>=3.2.0)
Requires-Dist: ckanext-query-dois (>=2.2.0)
Requires-Dist: ckanext-statistics (>=3.0.0)
Requires-Dist: ckanext-versioned-datastore (>=3.7.0)
Provides-Extra: test
Requires-Dist: mock ; extra == 'test'
Requires-Dist: pytest (>=4.6.5) ; extra == 'test'
Requires-Dist: pytest-cov (>=2.7.1) ; extra == 'test'
Requires-Dist: coveralls ; extra == 'test'
